{"data_mtime":1761494447,"dep_lines":[69,71,72,73,76,98,43,44,45,46,47,48,49,58,59,60,61,62,63,70,77,85,86,87,94,95,96,97,100,16,38,43,53,54,55,56,78,84,85,99,1,2,3,4,5,6,7,8,9,10,11,12,13,14,15,17,18,19,42,1048,1,1,1,1,1,1,1,1,40,1211],"dep_prios":[5,5,5,5,5,5,10,10,10,10,10,10,10,5,10,5,5,5,5,5,5,5,5,5,5,5,5,5,5,5,5,20,5,10,10,10,5,5,20,5,10,10,10,10,10,10,10,10,10,10,10,10,10,10,5,5,5,5,5,20,5,30,30,30,30,30,30,30,10,20],"dependencies":["ray._private.ray_logging.logging_config","ray._private.runtime_env.constants","ray._private.runtime_env.py_modules","ray._private.runtime_env.setup_hook","ray._private.runtime_env.working_dir","ray.util.tracing.tracing_helper","ray._private.node","ray._private.parameter","ray._private.profiling","ray._private.ray_constants","ray._private.serialization","ray._private.services","ray._private.state","ray._common.utils","ray._private.ray_option_utils","ray._private.client_mode_hook","ray._private.function_manager","ray._private.inspect_util","ray._private.ray_logging","ray._private.resource_isolation_config","ray._private.utils","ray.experimental.tqdm_ray","ray.experimental.compiled_dag_ref","ray.experimental.internal_kv","ray.runtime_env.runtime_env","ray.util.annotations","ray.util.debug","ray.util.scheduling_strategies","ray.widgets.util","collections.abc","urllib.parse","ray._private","ray.actor","ray.cloudpickle","ray.job_config","ray.remote_function","ray._raylet","ray.exceptions","ray.experimental","ray.widgets","atexit","faulthandler","functools","inspect","io","json","logging","os","sys","threading","time","traceback","urllib","warnings","abc","contextlib","dataclasses","typing","ray","re","builtins","_frozen_importlib","_thread","_typeshed","ray.experimental.gpu_object_manager","ray.experimental.gpu_object_manager.gpu_object_manager","ray.util","types"],"hash":"2919e22cfeb61a7a8ad23776ff80b412d5e7fa32","id":"ray._private.worker","ignore_all":true,"interface_hash":"f4f4225509591267379ef9c7fda57c8aa4bc90ad","mtime":1754107782,"options":{"allow_redefinition":false,"allow_redefinition_new":false,"allow_untyped_globals":false,"always_false":[],"always_true":[],"bazel":false,"check_untyped_defs":true,"disable_bytearray_promotion":false,"disable_error_code":[],"disable_memoryview_promotion":false,"disabled_error_codes":[],"disallow_any_decorated":false,"disallow_any_explicit":false,"disallow_any_expr":false,"disallow_any_generics":false,"disallow_any_unimported":false,"disallow_incomplete_defs":true,"disallow_subclassing_any":false,"disallow_untyped_calls":false,"disallow_untyped_decorators":true,"disallow_untyped_defs":true,"enable_error_code":[],"enabled_error_codes":[],"extra_checks":false,"fixed_format_cache":false,"follow_imports":"normal","follow_imports_for_stubs":false,"follow_untyped_imports":false,"ignore_errors":false,"ignore_missing_imports":false,"implicit_optional":false,"implicit_reexport":true,"local_partial_types":false,"mypyc":false,"old_type_inference":false,"platform":"linux","plugins":[],"strict_bytes":false,"strict_concatenate":false,"strict_equality":true,"strict_equality_for_none":false,"strict_optional":true,"warn_no_return":true,"warn_return_any":true,"warn_unreachable":true,"warn_unused_ignores":true},"path":"/home/a/.local/lib/python3.12/site-packages/ray/_private/worker.py","plugin_data":null,"size":138770,"suppressed":["colorama","ipywidgets"],"version_id":"1.18.2"}