{".class":"MypyFile","_fullname":"ray.data._internal.planner.planner","future_import_flags":[],"is_partial_stub_package":false,"is_stub":false,"names":{".class":"SymbolTable","Callable":{".class":"SymbolTableNode","cross_ref":"typing.Callable","kind":"Gdef"},"DataContext":{".class":"SymbolTableNode","cross_ref":"ray.data.context.DataContext","kind":"Gdef"},"DeveloperAPI":{".class":"SymbolTableNode","cross_ref":"ray.util.annotations.DeveloperAPI","kind":"Gdef"},"Dict":{".class":"SymbolTableNode","cross_ref":"typing.Dict","kind":"Gdef"},"Join":{".class":"SymbolTableNode","cross_ref":"ray.data._internal.logical.operators.join_operator.Join","kind":"Gdef"},"JoinOperator":{".class":"SymbolTableNode","cross_ref":"ray.data._internal.execution.operators.join.JoinOperator","kind":"Gdef"},"List":{".class":"SymbolTableNode","cross_ref":"typing.List","kind":"Gdef"},"LogicalOperator":{".class":"SymbolTableNode","cross_ref":"ray.data._internal.logical.interfaces.logical_operator.LogicalOperator","kind":"Gdef"},"LogicalOperatorType":{".class":"SymbolTableNode","kind":"Gdef","node":{".class":"TypeVarExpr","default":{".class":"AnyType","missing_import_name":null,"source_any":null,"type_of_any":4},"fullname":"ray.data._internal.planner.planner.LogicalOperatorType","name":"LogicalOperatorType","upper_bound":"ray.data._internal.logical.interfaces.logical_operator.LogicalOperator","values":[],"variance":0}},"LogicalPlan":{".class":"SymbolTableNode","cross_ref":"ray.data._internal.logical.interfaces.logical_plan.LogicalPlan","kind":"Gdef"},"PhysicalOperator":{".class":"SymbolTableNode","cross_ref":"ray.data._internal.execution.interfaces.physical_operator.PhysicalOperator","kind":"Gdef"},"PhysicalPlan":{".class":"SymbolTableNode","cross_ref":"ray.data._internal.logical.interfaces.physical_plan.PhysicalPlan","kind":"Gdef"},"PlanLogicalOpFn":{".class":"SymbolTableNode","kind":"Gdef","node":{".class":"TypeAlias","alias_tvars":[{".class":"TypeVarType","default":{".class":"AnyType","missing_import_name":null,"source_any":null,"type_of_any":4},"fullname":"ray.data._internal.planner.planner.LogicalOperatorType","id":1,"name":"LogicalOperatorType","namespace":"ray.data._internal.planner.planner.PlanLogicalOpFn","upper_bound":"ray.data._internal.logical.interfaces.logical_operator.LogicalOperator","values":[],"variance":0}],"column":0,"fullname":"ray.data._internal.planner.planner.PlanLogicalOpFn","line":16,"no_args":false,"normalized":false,"python_3_12_type_alias":false,"target":{".class":"CallableType","arg_kinds":[0,0,0],"arg_names":[null,null,null],"arg_types":[{".class":"TypeVarType","default":{".class":"AnyType","missing_import_name":null,"source_any":null,"type_of_any":4},"fullname":"ray.data._internal.planner.planner.LogicalOperatorType","id":1,"name":"LogicalOperatorType","namespace":"ray.data._internal.planner.planner.PlanLogicalOpFn","upper_bound":"ray.data._internal.logical.interfaces.logical_operator.LogicalOperator","values":[],"variance":0},{".class":"Instance","args":["ray.data._internal.execution.interfaces.physical_operator.PhysicalOperator"],"extra_attrs":null,"type_ref":"builtins.list"},"ray.data.context.DataContext"],"fallback":"builtins.function","from_concatenate":false,"implicit":false,"imprecise_arg_kinds":false,"is_bound":false,"is_ellipsis_args":false,"name":null,"ret_type":"ray.data._internal.execution.interfaces.physical_operator.PhysicalOperator","type_guard":null,"type_is":null,"unpack_kwargs":false,"variables":[]}}},"Planner":{".class":"SymbolTableNode","kind":"Gdef","node":{".class":"TypeInfo","_promote":[],"abstract_attributes":[],"alt_promote":null,"bases":["builtins.object"],"dataclass_transform_spec":null,"declared_metaclass":null,"defn":{".class":"ClassDef","fullname":"ray.data._internal.planner.planner.Planner","name":"Planner","type_vars":[]},"deletable_attributes":[],"deprecated":null,"flags":[],"fullname":"ray.data._internal.planner.planner.Planner","has_param_spec_type":false,"metaclass_type":null,"metadata":{},"module_name":"ray.data._internal.planner.planner","mro":["ray.data._internal.planner.planner.Planner","builtins.object"],"names":{".class":"SymbolTable","plan":{".class":"SymbolTableNode","kind":"Mdef","node":{".class":"FuncDef","abstract_status":0,"arg_kinds":[0,0],"arg_names":["self","logical_plan"],"dataclass_transform_spec":null,"deprecated":null,"flags":["is_trivial_self"],"fullname":"ray.data._internal.planner.planner.Planner.plan","name":"plan","original_first_arg":"self","type":{".class":"CallableType","arg_kinds":[0,0],"arg_names":["self","logical_plan"],"arg_types":["ray.data._internal.planner.planner.Planner","ray.data._internal.logical.interfaces.logical_plan.LogicalPlan"],"fallback":"builtins.function","from_concatenate":false,"implicit":false,"imprecise_arg_kinds":false,"is_bound":false,"is_ellipsis_args":false,"name":"plan of Planner","ret_type":"ray.data._internal.logical.interfaces.physical_plan.PhysicalPlan","type_guard":null,"type_is":null,"unpack_kwargs":false,"variables":[]}}}},"self_type":{".class":"TypeVarType","default":{".class":"AnyType","missing_import_name":null,"source_any":null,"type_of_any":4},"fullname":"ray.data._internal.planner.planner.Planner.Self","id":0,"name":"Self","namespace":"","upper_bound":"ray.data._internal.planner.planner.Planner","values":[],"variance":0},"slots":null,"tuple_type":null,"type_vars":[],"typeddict_type":null}},"Tuple":{".class":"SymbolTableNode","cross_ref":"typing.Tuple","kind":"Gdef"},"Type":{".class":"SymbolTableNode","cross_ref":"typing.Type","kind":"Gdef"},"TypeVar":{".class":"SymbolTableNode","cross_ref":"typing.TypeVar","kind":"Gdef"},"_PLAN_LOGICAL_OP_FNS":{".class":"SymbolTableNode","kind":"Gdef","node":{".class":"Var","flags":["is_ready","has_explicit_value"],"fullname":"ray.data._internal.planner.planner._PLAN_LOGICAL_OP_FNS","name":"_PLAN_LOGICAL_OP_FNS","setter_type":null,"type":{".class":"Instance","args":[{".class":"TypeType","item":"ray.data._internal.logical.interfaces.logical_operator.LogicalOperator"},{".class":"TypeAliasType","args":[{".class":"AnyType","missing_import_name":null,"source_any":null,"type_of_any":4}],"type_ref":"ray.data._internal.planner.planner.PlanLogicalOpFn"}],"extra_attrs":null,"type_ref":"builtins.dict"}}},"__annotations__":{".class":"SymbolTableNode","kind":"Gdef","node":{".class":"Var","flags":["is_ready"],"fullname":"ray.data._internal.planner.planner.__annotations__","name":"__annotations__","setter_type":null,"type":{".class":"Instance","args":["builtins.str",{".class":"AnyType","missing_import_name":null,"source_any":null,"type_of_any":6}],"extra_attrs":null,"type_ref":"builtins.dict"}}},"__doc__":{".class":"SymbolTableNode","kind":"Gdef","node":{".class":"Var","flags":["is_ready"],"fullname":"ray.data._internal.planner.planner.__doc__","name":"__doc__","setter_type":null,"type":"builtins.str"}},"__file__":{".class":"SymbolTableNode","kind":"Gdef","node":{".class":"Var","flags":["is_ready"],"fullname":"ray.data._internal.planner.planner.__file__","name":"__file__","setter_type":null,"type":"builtins.str"}},"__name__":{".class":"SymbolTableNode","kind":"Gdef","node":{".class":"Var","flags":["is_ready"],"fullname":"ray.data._internal.planner.planner.__name__","name":"__name__","setter_type":null,"type":"builtins.str"}},"__package__":{".class":"SymbolTableNode","kind":"Gdef","node":{".class":"Var","flags":["is_ready"],"fullname":"ray.data._internal.planner.planner.__package__","name":"__package__","setter_type":null,"type":"builtins.str"}},"__spec__":{".class":"SymbolTableNode","kind":"Gdef","node":{".class":"Var","flags":["is_ready"],"fullname":"ray.data._internal.planner.planner.__spec__","name":"__spec__","setter_type":null,"type":"_frozen_importlib.ModuleSpec"}},"_register_default_plan_logical_op_fns":{".class":"SymbolTableNode","kind":"Gdef","node":{".class":"FuncDef","abstract_status":0,"arg_kinds":[],"arg_names":[],"dataclass_transform_spec":null,"deprecated":null,"flags":[],"fullname":"ray.data._internal.planner.planner._register_default_plan_logical_op_fns","name":"_register_default_plan_logical_op_fns","original_first_arg":null,"type":null}},"get_plan_logical_op_fns":{".class":"SymbolTableNode","kind":"Gdef","node":{".class":"Decorator","func":{".class":"FuncDef","abstract_status":0,"arg_kinds":[],"arg_names":[],"dataclass_transform_spec":null,"deprecated":null,"flags":["is_decorated"],"fullname":"ray.data._internal.planner.planner.get_plan_logical_op_fns","name":"get_plan_logical_op_fns","original_first_arg":null,"type":null},"is_overload":false,"var":{".class":"Var","flags":["is_ready","is_inferred"],"fullname":"ray.data._internal.planner.planner.get_plan_logical_op_fns","name":"get_plan_logical_op_fns","setter_type":null,"type":{".class":"AnyType","missing_import_name":null,"source_any":null,"type_of_any":1}}}},"plan_recursively":{".class":"SymbolTableNode","kind":"Gdef","node":{".class":"Decorator","func":{".class":"FuncDef","abstract_status":0,"arg_kinds":[0,0,0],"arg_names":["logical_op","plan_fns","data_context"],"dataclass_transform_spec":null,"deprecated":null,"flags":["is_decorated"],"fullname":"ray.data._internal.planner.planner.plan_recursively","name":"plan_recursively","original_first_arg":"logical_op","type":{".class":"CallableType","arg_kinds":[0,0,0],"arg_names":["logical_op","plan_fns","data_context"],"arg_types":["ray.data._internal.logical.interfaces.logical_operator.LogicalOperator",{".class":"Instance","args":[{".class":"TypeType","item":"ray.data._internal.logical.interfaces.logical_operator.LogicalOperator"},{".class":"TypeAliasType","args":[{".class":"AnyType","missing_import_name":null,"source_any":null,"type_of_any":4}],"type_ref":"ray.data._internal.planner.planner.PlanLogicalOpFn"}],"extra_attrs":null,"type_ref":"builtins.dict"},"ray.data.context.DataContext"],"fallback":"builtins.function","from_concatenate":false,"implicit":false,"imprecise_arg_kinds":false,"is_bound":false,"is_ellipsis_args":false,"name":"plan_recursively","ret_type":{".class":"TupleType","implicit":false,"items":["ray.data._internal.execution.interfaces.physical_operator.PhysicalOperator",{".class":"Instance","args":["ray.data._internal.execution.interfaces.physical_operator.PhysicalOperator","ray.data._internal.logical.interfaces.logical_operator.LogicalOperator"],"extra_attrs":null,"type_ref":"builtins.dict"}],"partial_fallback":{".class":"Instance","args":[{".class":"AnyType","missing_import_name":null,"source_any":null,"type_of_any":6}],"extra_attrs":null,"type_ref":"builtins.tuple"}},"type_guard":null,"type_is":null,"unpack_kwargs":false,"variables":[]}},"is_overload":false,"var":{".class":"Var","flags":["is_ready","is_inferred"],"fullname":"ray.data._internal.planner.planner.plan_recursively","name":"plan_recursively","setter_type":null,"type":{".class":"AnyType","missing_import_name":null,"source_any":null,"type_of_any":1}}}},"register_plan_logical_op_fn":{".class":"SymbolTableNode","kind":"Gdef","node":{".class":"Decorator","func":{".class":"FuncDef","abstract_status":0,"arg_kinds":[0,0],"arg_names":["logical_op_type","plan_fn"],"dataclass_transform_spec":null,"deprecated":null,"flags":["is_decorated"],"fullname":"ray.data._internal.planner.planner.register_plan_logical_op_fn","name":"register_plan_logical_op_fn","original_first_arg":"logical_op_type","type":{".class":"CallableType","arg_kinds":[0,0],"arg_names":["logical_op_type","plan_fn"],"arg_types":[{".class":"TypeType","item":"ray.data._internal.logical.interfaces.logical_operator.LogicalOperator"},{".class":"TypeAliasType","args":[{".class":"AnyType","missing_import_name":null,"source_any":null,"type_of_any":4}],"type_ref":"ray.data._internal.planner.planner.PlanLogicalOpFn"}],"fallback":"builtins.function","from_concatenate":false,"implicit":false,"imprecise_arg_kinds":false,"is_bound":false,"is_ellipsis_args":false,"name":"register_plan_logical_op_fn","ret_type":{".class":"AnyType","missing_import_name":null,"source_any":null,"type_of_any":1},"type_guard":null,"type_is":null,"unpack_kwargs":false,"variables":[]}},"is_overload":false,"var":{".class":"Var","flags":["is_ready","is_inferred"],"fullname":"ray.data._internal.planner.planner.register_plan_logical_op_fn","name":"register_plan_logical_op_fn","setter_type":null,"type":{".class":"AnyType","missing_import_name":null,"source_any":null,"type_of_any":1}}}}},"path":"/home/a/.local/lib/python3.12/site-packages/ray/data/_internal/planner/planner.py"}